pulpitum
