Metadata-Version: 1.1
Name: pulpitum
Version: 0.2.2
Summary: PyPI client for Humans™
Home-page: https://github.com/requirements/pulpitum
Author: Sofia Velmer
Author-email: me@require.pm
License: GNU GPLv3
Keywords: pypi packages
Platform: All
Classifier: Intended Audience :: Developers
Classifier: Development Status :: 3 - Alpha
Classifier: Operating System :: OS Independent
Classifier: Programming Language :: Python
Classifier: Programming Language :: Python :: 2.7
Classifier: Programming Language :: Python :: 3.3
Classifier: License :: OSI Approved :: GNU General Public License v3 (GPLv3)
Provides: pulpitum
